{
	"froze solid": "冻得硬邦邦的",
	"battle their way through": "艰难通过",
	"deliver": "派送",
	"measure": "测量",
	"ignore": "忽略",
	"be impressed at": "留有深刻的好印象",
	"jealous": "嫉妒",
	"proper": "名副其实的",
	"sticking out at the bottom": "从底部伸出来",
	"earn some extra money": "赚外快",
	"compared to": "做比较",
	"grateful": "感激的",
	"grinding his teeth at": "咬牙切齿",
	"decoration": "装饰",
	"icicle": "冰柱",
	"tearing his eyes away from": "恋恋不舍地把目光移开",
	"mentioned": "提及",
	"save us the trouble": "帮我们免去麻烦",
	"give us a hint": "给我们一点暗示",
	"indeed": "事实上",
	"notable": "著名的",
	"recent": "最近的",
	"the sheer size of": "规模庞大的",
	"at random": "随机的",
	"the Restricted Section": "受限制区域",
	"contain": "包含",
	"librarian": "图书管理员",
	"shouting different bits of advice at": "嚷嚷着不同建议",
	"obviously": "明显的",
	"valuable": "有价值的",
	"invisibility": "看不见的东西",
	"reflection": "倒影",
	"invisible": "无形的",
	"left this in my possession": "把这个留给我保管",
	"signature": "签名",
	"admiring": "羡慕",
	"effort": "付出",
	"demanded": "强烈要求",
	"halfheartedly": "半不情愿地",
	"observed": "观察"
}